[{"id":"9401","province_id":"94","name":"KABUPATEN MERAUKE","rajaongkir_city_id":"281"},{"id":"9402","province_id":"94","name":"KABUPATEN JAYAWIJAYA","rajaongkir_city_id":"159"},{"id":"9403","province_id":"94","name":"KABUPATEN JAYAPURA","rajaongkir_city_id":"157"},{"id":"9404","province_id":"94","name":"KABUPATEN NABIRE","rajaongkir_city_id":"299"},{"id":"9408","province_id":"94","name":"KABUPATEN KEPULAUAN YAPEN","rajaongkir_city_id":"193"},{"id":"9409","province_id":"94","name":"KABUPATEN BIAK NUMFOR","rajaongkir_city_id":"67"},{"id":"9410","province_id":"94","name":"KABUPATEN PANIAI","rajaongkir_city_id":"335"},{"id":"9411","province_id":"94","name":"KABUPATEN PUNCAK JAYA","rajaongkir_city_id":"374"},{"id":"9412","province_id":"94","name":"KABUPATEN MIMIKA","rajaongkir_city_id":"284"},{"id":"9413","province_id":"94","name":"KABUPATEN BOVEN DIGOEL","rajaongkir_city_id":"90"},{"id":"9414","province_id":"94","name":"KABUPATEN MAPPI","rajaongkir_city_id":"274"},{"id":"9415","province_id":"94","name":"KABUPATEN ASMAT","rajaongkir_city_id":"16"},{"id":"9416","province_id":"94","name":"KABUPATEN YAHUKIMO","rajaongkir_city_id":"499"},{"id":"9417","province_id":"94","name":"KABUPATEN PEGUNUNGAN BINTANG","rajaongkir_city_id":"347"},{"id":"9418","province_id":"94","name":"KABUPATEN TOLIKARA","rajaongkir_city_id":"484"},{"id":"9419","province_id":"94","name":"KABUPATEN SARMI","rajaongkir_city_id":"392"},{"id":"9420","province_id":"94","name":"KABUPATEN KEEROM","rajaongkir_city_id":"180"},{"id":"9426","province_id":"94","name":"KABUPATEN WAROPEN","rajaongkir_city_id":"495"},{"id":"9427","province_id":"94","name":"KABUPATEN SUPIORI","rajaongkir_city_id":"443"},{"id":"9428","province_id":"94","name":"KABUPATEN MAMBERAMO RAYA","rajaongkir_city_id":"263"},{"id":"9429","province_id":"94","name":"KABUPATEN NDUGA","rajaongkir_city_id":"303"},{"id":"9430","province_id":"94","name":"KABUPATEN LANNY JAYA","rajaongkir_city_id":"231"},{"id":"9431","province_id":"94","name":"KABUPATEN MAMBERAMO TENGAH","rajaongkir_city_id":"264"},{"id":"9432","province_id":"94","name":"KABUPATEN YALIMO","rajaongkir_city_id":"500"},{"id":"9433","province_id":"94","name":"KABUPATEN PUNCAK","rajaongkir_city_id":"373"},{"id":"9434","province_id":"94","name":"KABUPATEN DOGIYAI","rajaongkir_city_id":"117"},{"id":"9435","province_id":"94","name":"KABUPATEN INTAN JAYA","rajaongkir_city_id":"150"},{"id":"9436","province_id":"94","name":"KABUPATEN DEIYAI","rajaongkir_city_id":"111"},{"id":"9471","province_id":"94","name":"KOTA JAYAPURA","rajaongkir_city_id":"158"}]